laonlp_enhanced/__init__.py
laonlp_enhanced/dictionary.txt
laonlp_enhanced/lao_tokenizer.json
laonlp_enhanced/stopwords.txt
laonlp_enhanced/tokenize.py
laonlp_enhanced-0.1.1.dist-info/METADATA
laonlp_enhanced-0.1.1.dist-info/WHEEL
laonlp_enhanced-0.1.1.dist-info/top_level.txt
laonlp_enhanced-0.1.1.dist-info/RECORD
