Metadata-Version: 2.1
Name: laonlp-enhanced
Version: 0.1.1
Summary: Enhanced Lao NLP tokenizer, compatible with laonlp POS tagging
Home-page: https://github.com/saypadith/laonlp-enhanced
Author: Savath Saypadith
Author-email: mr.saypadith@gmail.com
License: MIT
Classifier: Programming Language :: Python :: 3
Classifier: License :: OSI Approved :: MIT License
Requires-Dist: laonlp>=1.0.0
Requires-Dist: transformers>=4.0.0
Requires-Dist: tokenizers>=0.10.0
